{
  "self": [
    "api",
    "CanvasRenderingContext2D",
    "fillText"
  ],
  "type": "page",
  "title": "CanvasRenderingContext2D: fillText() method",
  "links": {
    "mdn": "https://developer.mozilla.org/docs/Web/API/CanvasRenderingContext2D/fillText",
    "spec": "https://html.spec.whatwg.org/multipage/canvas.html#dom-context-2d-filltext-dev",
    "github": "https://github.com/mdn/content/blob/main/files/en-us/web/api/canvasrenderingcontext2d/filltext/index.md"
  },
  "content": {
    "intro": {
      "id": "e43bb46ddacb2a908d85fdaca5c560d6",
      "tree": {
        "type": "root",
        "children": [
          {
            "type": "element",
            "tagName": "p",
            "properties": {},
            "children": [
              {
                "type": "text",
                "value": "The "
              },
              {
                "type": "element",
                "tagName": "a",
                "properties": {
                  "internal": "",
                  "href": "/api/CanvasRenderingContext2D"
                },
                "children": [
                  {
                    "type": "element",
                    "tagName": "code",
                    "properties": {},
                    "children": [
                      {
                        "type": "text",
                        "value": "CanvasRenderingContext2D"
                      }
                    ]
                  }
                ]
              },
              {
                "type": "text",
                "value": " method\n"
              },
              {
                "type": "element",
                "tagName": "strong",
                "properties": {},
                "children": [
                  {
                    "type": "element",
                    "tagName": "code",
                    "properties": {},
                    "children": [
                      {
                        "type": "text",
                        "value": "fillText()"
                      }
                    ]
                  }
                ]
              },
              {
                "type": "text",
                "value": ", part of the Canvas 2D API, draws a text string\nat the specified coordinates, filling the string's characters with the current\n"
              },
              {
                "type": "element",
                "tagName": "a",
                "properties": {
                  "internal": "",
                  "href": "/api/CanvasRenderingContext2D/fillStyle"
                },
                "children": [
                  {
                    "type": "element",
                    "tagName": "code",
                    "properties": {},
                    "children": [
                      {
                        "type": "text",
                        "value": "fillStyle"
                      }
                    ]
                  }
                ]
              },
              {
                "type": "text",
                "value": ". An optional parameter\nallows specifying a maximum width for the rendered text, which the {{Glossary(\"user\nagent\")}} will achieve by condensing the text or by using a lower font size."
              }
            ]
          }
        ],
        "data": {
          "quirksMode": false
        }
      }
    },
    "seeAlso": {
      "id": "48f3ef881b738883e261107ce51c29dd",
      "tree": {
        "type": "root",
        "children": [
          {
            "type": "element",
            "tagName": "ul",
            "properties": {},
            "children": [
              {
                "type": "text",
                "value": "\n"
              },
              {
                "type": "element",
                "tagName": "li",
                "properties": {},
                "children": [
                  {
                    "type": "element",
                    "tagName": "a",
                    "properties": {
                      "href": "/en-US/docs/Web/API/Canvas_API/Tutorial/Drawing_text"
                    },
                    "children": [
                      {
                        "type": "text",
                        "value": "Drawing text"
                      }
                    ]
                  }
                ]
              },
              {
                "type": "text",
                "value": "\n"
              },
              {
                "type": "element",
                "tagName": "li",
                "properties": {},
                "children": [
                  {
                    "type": "element",
                    "tagName": "a",
                    "properties": {
                      "internal": "",
                      "href": "/api/CanvasRenderingContext2D"
                    },
                    "children": [
                      {
                        "type": "element",
                        "tagName": "code",
                        "properties": {},
                        "children": [
                          {
                            "type": "text",
                            "value": "CanvasRenderingContext2D"
                          }
                        ]
                      }
                    ]
                  }
                ]
              },
              {
                "type": "text",
                "value": "\n"
              },
              {
                "type": "element",
                "tagName": "li",
                "properties": {},
                "children": [
                  {
                    "type": "element",
                    "tagName": "a",
                    "properties": {
                      "internal": "",
                      "href": "/api/CanvasRenderingContext2D/strokeText"
                    },
                    "children": [
                      {
                        "type": "element",
                        "tagName": "code",
                        "properties": {},
                        "children": [
                          {
                            "type": "text",
                            "value": "CanvasRenderingContext2D.strokeText()"
                          }
                        ]
                      }
                    ]
                  }
                ]
              },
              {
                "type": "text",
                "value": "\n"
              }
            ]
          }
        ],
        "data": {
          "quirksMode": false
        }
      }
    }
  },
  "commit": {
    "sha": "1f216a70d94c3901c5767e6108a29daa48edc070",
    "date": "2023-04-07T06:13:50.000Z"
  },
  "usage": 0.9629300000000002,
  "support": {
    "chrome": {
      "name": "Chrome",
      "added": {
        "version": "2.0.0",
        "date": 1242864000
      },
      "removed": null,
      "usage": {
        "global": 0.2667000000000001,
        "relative": 1
      },
      "history": [
        {
          "notes": null,
          "added": {
            "version": "2.0.0",
            "date": 1242864000
          },
          "removed": null,
          "usage": {
            "global": 0.2667000000000001,
            "relative": 1
          }
        }
      ]
    },
    "chrome_android": {
      "name": "Chrome Android",
      "added": {
        "version": "18.0.0",
        "date": 1340755200
      },
      "removed": null,
      "usage": {
        "global": 0.34070000000000017,
        "relative": 1
      },
      "history": [
        {
          "notes": null,
          "added": {
            "version": "18.0.0",
            "date": 1340755200
          },
          "removed": null,
          "usage": {
            "global": 0.34070000000000017,
            "relative": 1
          }
        }
      ]
    },
    "edge": {
      "name": "Edge",
      "added": {
        "version": "12.0.0",
        "date": 1438041600
      },
      "removed": null,
      "usage": {
        "global": 0.05069999999999997,
        "relative": 1
      },
      "history": [
        {
          "notes": null,
          "added": {
            "version": "12.0.0",
            "date": 1438041600
          },
          "removed": null,
          "usage": {
            "global": 0.05069999999999997,
            "relative": 1
          }
        }
      ]
    },
    "firefox": {
      "name": "Firefox",
      "added": {
        "version": "3.5.0",
        "date": 1246320000
      },
      "removed": null,
      "usage": {
        "global": 0.029399999999999985,
        "relative": 1
      },
      "history": [
        {
          "notes": null,
          "added": {
            "version": "3.5.0",
            "date": 1246320000
          },
          "removed": null,
          "usage": {
            "global": 0.029399999999999985,
            "relative": 1
          }
        }
      ]
    },
    "firefox_android": {
      "name": "Firefox for Android",
      "added": {
        "version": "4.0.0",
        "date": 1301356800
      },
      "removed": null,
      "usage": {
        "global": null,
        "relative": null
      },
      "history": [
        {
          "notes": null,
          "added": {
            "version": "4.0.0",
            "date": 1301356800
          },
          "removed": null,
          "usage": {
            "global": null,
            "relative": null
          }
        }
      ]
    },
    "ie": {
      "name": "Internet Explorer",
      "added": {
        "version": "9.0.0",
        "date": 1300060800
      },
      "removed": null,
      "usage": {
        "global": 0.0015,
        "relative": 1
      },
      "history": [
        {
          "notes": null,
          "added": {
            "version": "9.0.0",
            "date": 1300060800
          },
          "removed": null,
          "usage": {
            "global": 0.0015,
            "relative": 1
          }
        }
      ]
    },
    "oculus": {
      "name": "Quest Browser",
      "added": {
        "version": "5.0.0",
        "date": null
      },
      "removed": null,
      "usage": {
        "global": null,
        "relative": null
      },
      "history": [
        {
          "notes": null,
          "added": {
            "version": "5.0.0",
            "date": null
          },
          "removed": null,
          "usage": {
            "global": null,
            "relative": null
          }
        }
      ]
    },
    "opera": {
      "name": "Opera",
      "added": {
        "version": "12.1.0",
        "date": 1353369600
      },
      "removed": null,
      "usage": {
        "global": 0.02789999999999999,
        "relative": 1
      },
      "history": [
        {
          "notes": null,
          "added": {
            "version": "12.1.0",
            "date": 1353369600
          },
          "removed": null,
          "usage": {
            "global": 0.02789999999999999,
            "relative": 1
          }
        }
      ]
    },
    "opera_android": {
      "name": "Opera Android",
      "added": {
        "version": "12.1.0",
        "date": 1349740800
      },
      "removed": null,
      "usage": {
        "global": null,
        "relative": null
      },
      "history": [
        {
          "notes": null,
          "added": {
            "version": "12.1.0",
            "date": 1349740800
          },
          "removed": null,
          "usage": {
            "global": null,
            "relative": null
          }
        }
      ]
    },
    "safari": {
      "name": "Safari",
      "added": {
        "version": "4.0.0",
        "date": 1244419200
      },
      "removed": null,
      "usage": {
        "global": 0.0592,
        "relative": 1
      },
      "history": [
        {
          "notes": null,
          "added": {
            "version": "4.0.0",
            "date": 1244419200
          },
          "removed": null,
          "usage": {
            "global": 0.0592,
            "relative": 1
          }
        }
      ]
    },
    "safari_ios": {
      "name": "Safari on iOS",
      "added": {
        "version": "3.2.0",
        "date": 1270252800
      },
      "removed": null,
      "usage": {
        "global": 0.16352999999999998,
        "relative": 1
      },
      "history": [
        {
          "notes": null,
          "added": {
            "version": "3.2.0",
            "date": 1270252800
          },
          "removed": null,
          "usage": {
            "global": 0.16352999999999998,
            "relative": 1
          }
        }
      ]
    },
    "samsunginternet_android": {
      "name": "Samsung Internet",
      "added": {
        "version": "1.0.0",
        "date": 1367020800
      },
      "removed": null,
      "usage": {
        "global": 0.023299999999999984,
        "relative": 1
      },
      "history": [
        {
          "notes": null,
          "added": {
            "version": "1.0.0",
            "date": 1367020800
          },
          "removed": null,
          "usage": {
            "global": 0.023299999999999984,
            "relative": 1
          }
        }
      ]
    },
    "webview_android": {
      "name": "WebView Android",
      "added": {
        "version": "37.0.0",
        "date": 1409702400
      },
      "removed": null,
      "usage": {
        "global": null,
        "relative": null
      },
      "history": [
        {
          "notes": null,
          "added": {
            "version": "37.0.0",
            "date": 1409702400
          },
          "removed": null,
          "usage": {
            "global": null,
            "relative": null
          }
        }
      ]
    }
  },
  "status": {
    "deprecated": false,
    "experimental": false,
    "standard_track": true
  }
}