{
  "self": [
    "api",
    "WebTransportDatagramDuplexStream",
    "outgoingHighWaterMark"
  ],
  "type": "page",
  "title": "WebTransportDatagramDuplexStream: outgoingHighWaterMark property",
  "links": {
    "mdn": "https://developer.mozilla.org/docs/Web/API/WebTransportDatagramDuplexStream/outgoingHighWaterMark",
    "spec": "https://w3c.github.io/webtransport/#dom-webtransportdatagramduplexstream-outgoinghighwatermark",
    "github": "https://github.com/mdn/content/blob/main/files/en-us/web/api/webtransportdatagramduplexstream/outgoinghighwatermark/index.md"
  },
  "content": {
    "intro": {
      "id": "eddb150247c6b2a3ca05fb41db1d2677",
      "tree": {
        "type": "root",
        "children": [
          {
            "type": "element",
            "tagName": "p",
            "properties": {},
            "children": [
              {
                "type": "text",
                "value": "The "
              },
              {
                "type": "element",
                "tagName": "strong",
                "properties": {},
                "children": [
                  {
                    "type": "element",
                    "tagName": "code",
                    "properties": {},
                    "children": [
                      {
                        "type": "text",
                        "value": "outgoingHighWaterMark"
                      }
                    ]
                  }
                ]
              },
              {
                "type": "text",
                "value": " property of the "
              },
              {
                "type": "element",
                "tagName": "a",
                "properties": {
                  "internal": "",
                  "href": "/api/WebTransportDatagramDuplexStream"
                },
                "children": [
                  {
                    "type": "element",
                    "tagName": "code",
                    "properties": {},
                    "children": [
                      {
                        "type": "text",
                        "value": "WebTransportDatagramDuplexStream"
                      }
                    ]
                  }
                ]
              },
              {
                "type": "text",
                "value": " interface gets or sets the high water mark for outgoing chunks of data — this is the maximum size, in chunks, that the outgoing "
              },
              {
                "type": "element",
                "tagName": "a",
                "properties": {
                  "internal": "",
                  "href": "/api/WritableStream"
                },
                "children": [
                  {
                    "type": "element",
                    "tagName": "code",
                    "properties": {},
                    "children": [
                      {
                        "type": "text",
                        "value": "WritableStream"
                      }
                    ]
                  }
                ]
              },
              {
                "type": "text",
                "value": "'s internal queue can reach before it is considered full. See "
              },
              {
                "type": "element",
                "tagName": "a",
                "properties": {
                  "href": "/en-US/docs/Web/API/Streams_API/Concepts#internal_queues_and_queuing_strategies"
                },
                "children": [
                  {
                    "type": "text",
                    "value": "Internal queues and queuing strategies"
                  }
                ]
              },
              {
                "type": "text",
                "value": " for more information."
              }
            ]
          }
        ],
        "data": {
          "quirksMode": false
        }
      }
    },
    "seeAlso": {
      "id": "82e6033812e631ee302d43ccf9646dc0",
      "tree": {
        "type": "root",
        "children": [
          {
            "type": "element",
            "tagName": "ul",
            "properties": {},
            "children": [
              {
                "type": "text",
                "value": "\n"
              },
              {
                "type": "element",
                "tagName": "li",
                "properties": {},
                "children": [
                  {
                    "type": "element",
                    "tagName": "a",
                    "properties": {
                      "href": "https://developer.chrome.com/docs/capabilities/web-apis/webtransport"
                    },
                    "children": [
                      {
                        "type": "text",
                        "value": "Using WebTransport"
                      }
                    ]
                  }
                ]
              },
              {
                "type": "text",
                "value": "\n"
              },
              {
                "type": "element",
                "tagName": "li",
                "properties": {},
                "children": [
                  {
                    "type": "element",
                    "tagName": "code",
                    "properties": {},
                    "children": [
                      {
                        "type": "text",
                        "value": "WebSockets API"
                      }
                    ]
                  }
                ]
              },
              {
                "type": "text",
                "value": "\n"
              },
              {
                "type": "element",
                "tagName": "li",
                "properties": {},
                "children": [
                  {
                    "type": "element",
                    "tagName": "code",
                    "properties": {},
                    "children": [
                      {
                        "type": "text",
                        "value": "Streams API"
                      }
                    ]
                  }
                ]
              },
              {
                "type": "text",
                "value": "\n"
              },
              {
                "type": "element",
                "tagName": "li",
                "properties": {},
                "children": [
                  {
                    "type": "element",
                    "tagName": "a",
                    "properties": {
                      "href": "https://datatracker.ietf.org/doc/html/draft-ietf-webtrans-http3/"
                    },
                    "children": [
                      {
                        "type": "text",
                        "value": "WebTransport over HTTP/3"
                      }
                    ]
                  }
                ]
              },
              {
                "type": "text",
                "value": "\n"
              }
            ]
          }
        ],
        "data": {
          "quirksMode": false
        }
      }
    }
  },
  "commit": {
    "sha": "4458494807b6f4898d504b6c0af0a45f8031cbf3",
    "date": "2023-12-10T06:28:37.000Z"
  },
  "usage": 0.7018599999999999,
  "support": {
    "chrome": {
      "name": "Chrome",
      "added": {
        "version": "97.0.0",
        "date": 1641254400
      },
      "removed": null,
      "usage": {
        "global": 0.25159999999999993,
        "relative": 0.9437359339834951
      },
      "history": [
        {
          "notes": null,
          "added": {
            "version": "97.0.0",
            "date": 1641254400
          },
          "removed": null,
          "usage": {
            "global": 0.25159999999999993,
            "relative": 0.9437359339834951
          }
        }
      ]
    },
    "chrome_android": {
      "name": "Chrome Android",
      "added": {
        "version": "97.0.0",
        "date": 1641254400
      },
      "removed": null,
      "usage": {
        "global": 0.33605999999999997,
        "relative": 0.9847046413502109
      },
      "history": [
        {
          "notes": null,
          "added": {
            "version": "97.0.0",
            "date": 1641254400
          },
          "removed": null,
          "usage": {
            "global": 0.33605999999999997,
            "relative": 0.9847046413502109
          }
        }
      ]
    },
    "edge": {
      "name": "Edge",
      "added": {
        "version": "97.0.0",
        "date": 1641427200
      },
      "removed": null,
      "usage": {
        "global": 0.048099999999999976,
        "relative": 0.9468503937007876
      },
      "history": [
        {
          "notes": null,
          "added": {
            "version": "97.0.0",
            "date": 1641427200
          },
          "removed": null,
          "usage": {
            "global": 0.048099999999999976,
            "relative": 0.9468503937007876
          }
        }
      ]
    },
    "firefox": {
      "name": "Firefox",
      "added": {
        "version": "114.0.0",
        "date": 1686009600
      },
      "removed": null,
      "usage": {
        "global": 0.0261,
        "relative": 0.8817567567567572
      },
      "history": [
        {
          "notes": null,
          "added": {
            "version": "114.0.0",
            "date": 1686009600
          },
          "removed": null,
          "usage": {
            "global": 0.0261,
            "relative": 0.8817567567567572
          }
        }
      ]
    },
    "firefox_android": {
      "name": "Firefox for Android",
      "added": {
        "version": "114.0.0",
        "date": 1686009600
      },
      "removed": null,
      "usage": {
        "global": null,
        "relative": null
      },
      "history": [
        {
          "notes": null,
          "added": {
            "version": "114.0.0",
            "date": 1686009600
          },
          "removed": null,
          "usage": {
            "global": null,
            "relative": null
          }
        }
      ]
    },
    "ie": {
      "name": "Internet Explorer",
      "added": null,
      "removed": null,
      "usage": {
        "global": null,
        "relative": null
      },
      "history": [
        {
          "notes": null,
          "added": null,
          "removed": null,
          "usage": {
            "global": null,
            "relative": null
          }
        }
      ]
    },
    "oculus": {
      "name": "Quest Browser",
      "added": {
        "version": "20.0.0",
        "date": 1647216000
      },
      "removed": null,
      "usage": {
        "global": null,
        "relative": null
      },
      "history": [
        {
          "notes": null,
          "added": {
            "version": "20.0.0",
            "date": 1647216000
          },
          "removed": null,
          "usage": {
            "global": null,
            "relative": null
          }
        }
      ]
    },
    "opera": {
      "name": "Opera",
      "added": {
        "version": "83.0.0",
        "date": 1642550400
      },
      "removed": null,
      "usage": {
        "global": 0.018800000000000004,
        "relative": 0.6787003610108306
      },
      "history": [
        {
          "notes": null,
          "added": {
            "version": "83.0.0",
            "date": 1642550400
          },
          "removed": null,
          "usage": {
            "global": 0.018800000000000004,
            "relative": 0.6787003610108306
          }
        }
      ]
    },
    "opera_android": {
      "name": "Opera Android",
      "added": {
        "version": "68.0.0",
        "date": 1648598400
      },
      "removed": null,
      "usage": {
        "global": null,
        "relative": null
      },
      "history": [
        {
          "notes": null,
          "added": {
            "version": "68.0.0",
            "date": 1648598400
          },
          "removed": null,
          "usage": {
            "global": null,
            "relative": null
          }
        }
      ]
    },
    "safari": {
      "name": "Safari",
      "added": null,
      "removed": null,
      "usage": {
        "global": null,
        "relative": null
      },
      "history": [
        {
          "notes": null,
          "added": null,
          "removed": null,
          "usage": {
            "global": null,
            "relative": null
          }
        }
      ]
    },
    "safari_ios": {
      "name": "Safari on iOS",
      "added": null,
      "removed": null,
      "usage": {
        "global": null,
        "relative": null
      },
      "history": [
        {
          "notes": null,
          "added": null,
          "removed": null,
          "usage": {
            "global": null,
            "relative": null
          }
        }
      ]
    },
    "samsunginternet_android": {
      "name": "Samsung Internet",
      "added": {
        "version": "18.0.0",
        "date": 1659916800
      },
      "removed": null,
      "usage": {
        "global": 0.0212,
        "relative": 0.9098712446351936
      },
      "history": [
        {
          "notes": null,
          "added": {
            "version": "18.0.0",
            "date": 1659916800
          },
          "removed": null,
          "usage": {
            "global": 0.0212,
            "relative": 0.9098712446351936
          }
        }
      ]
    },
    "webview_android": {
      "name": "WebView Android",
      "added": {
        "version": "97.0.0",
        "date": 1641254400
      },
      "removed": null,
      "usage": {
        "global": null,
        "relative": null
      },
      "history": [
        {
          "notes": null,
          "added": {
            "version": "97.0.0",
            "date": 1641254400
          },
          "removed": null,
          "usage": {
            "global": null,
            "relative": null
          }
        }
      ]
    }
  },
  "status": {
    "deprecated": false,
    "experimental": false,
    "standard_track": true
  }
}