{
  "self": [
    "api",
    "Navigator",
    "virtualKeyboard"
  ],
  "type": "page",
  "title": "Navigator / virtualKeyboard",
  "links": {
    "spec": "https://w3c.github.io/virtual-keyboard/#dom-navigator-virtualkeyboard"
  },
  "usage": 0.61934,
  "support": {
    "chrome": {
      "name": "Chrome",
      "added": {
        "version": "94.0.0",
        "date": 1632182400
      },
      "removed": null,
      "usage": {
        "global": 0.24350000000000002,
        "relative": 0.9192147980369947
      },
      "history": [
        {
          "notes": null,
          "added": {
            "version": "94.0.0",
            "date": 1632182400
          },
          "removed": null,
          "usage": {
            "global": 0.24350000000000002,
            "relative": 0.9192147980369947
          }
        }
      ]
    },
    "chrome_android": {
      "name": "Chrome Android",
      "added": {
        "version": "94.0.0",
        "date": 1632182400
      },
      "removed": null,
      "usage": {
        "global": 0.32594,
        "relative": 0.9005857648099026
      },
      "history": [
        {
          "notes": null,
          "added": {
            "version": "94.0.0",
            "date": 1632182400
          },
          "removed": null,
          "usage": {
            "global": 0.32594,
            "relative": 0.9005857648099026
          }
        }
      ]
    },
    "edge": {
      "name": "Edge",
      "added": {
        "version": "94.0.0",
        "date": 1632441600
      },
      "removed": null,
      "usage": {
        "global": 0.039799999999999995,
        "relative": 0.9754901960784315
      },
      "history": [
        {
          "notes": null,
          "added": {
            "version": "94.0.0",
            "date": 1632441600
          },
          "removed": null,
          "usage": {
            "global": 0.039799999999999995,
            "relative": 0.9754901960784315
          }
        }
      ]
    },
    "firefox": {
      "name": "Firefox",
      "added": null,
      "removed": null,
      "usage": {
        "global": null,
        "relative": null
      },
      "history": [
        {
          "notes": null,
          "added": null,
          "removed": null,
          "usage": {
            "global": null,
            "relative": null
          }
        }
      ]
    },
    "firefox_android": {
      "name": "Firefox for Android",
      "added": null,
      "removed": null,
      "usage": {
        "global": null,
        "relative": null
      },
      "history": [
        {
          "notes": null,
          "added": null,
          "removed": null,
          "usage": {
            "global": null,
            "relative": null
          }
        }
      ]
    },
    "ie": {
      "name": "Internet Explorer",
      "added": null,
      "removed": null,
      "usage": {
        "global": null,
        "relative": null
      },
      "history": [
        {
          "notes": null,
          "added": null,
          "removed": null,
          "usage": {
            "global": null,
            "relative": null
          }
        }
      ]
    },
    "opera": {
      "name": "Opera",
      "added": {
        "version": "80.0.0",
        "date": 1633392000
      },
      "removed": null,
      "usage": {
        "global": 0.0101,
        "relative": 0.5580110497237568
      },
      "history": [
        {
          "notes": null,
          "added": {
            "version": "80.0.0",
            "date": 1633392000
          },
          "removed": null,
          "usage": {
            "global": 0.0101,
            "relative": 0.5580110497237568
          }
        }
      ]
    },
    "opera_android": {
      "name": "Opera Android",
      "added": {
        "version": "66.0.0",
        "date": 1639526400
      },
      "removed": null,
      "usage": {
        "global": null,
        "relative": null
      },
      "history": [
        {
          "notes": null,
          "added": {
            "version": "66.0.0",
            "date": 1639526400
          },
          "removed": null,
          "usage": {
            "global": null,
            "relative": null
          }
        }
      ]
    },
    "safari": {
      "name": "Safari",
      "added": null,
      "removed": null,
      "usage": {
        "global": null,
        "relative": null
      },
      "history": [
        {
          "notes": null,
          "added": null,
          "removed": null,
          "usage": {
            "global": null,
            "relative": null
          }
        }
      ]
    },
    "safari_ios": {
      "name": "Safari on iOS",
      "added": null,
      "removed": null,
      "usage": {
        "global": null,
        "relative": null
      },
      "history": [
        {
          "notes": null,
          "added": null,
          "removed": null,
          "usage": {
            "global": null,
            "relative": null
          }
        }
      ]
    },
    "samsunginternet_android": {
      "name": "Samsung Internet",
      "added": null,
      "removed": null,
      "usage": {
        "global": null,
        "relative": null
      },
      "history": [
        {
          "notes": null,
          "added": null,
          "removed": null,
          "usage": {
            "global": null,
            "relative": null
          }
        }
      ]
    },
    "webview_android": {
      "name": "WebView Android",
      "added": {
        "version": "94.0.0",
        "date": 1632182400
      },
      "removed": null,
      "usage": {
        "global": null,
        "relative": null
      },
      "history": [
        {
          "notes": null,
          "added": {
            "version": "94.0.0",
            "date": 1632182400
          },
          "removed": null,
          "usage": {
            "global": null,
            "relative": null
          }
        }
      ]
    }
  },
  "status": {
    "experimental": true,
    "standard_track": true,
    "deprecated": false
  }
}