{
  "self": [
    "api",
    "TextMetrics"
  ],
  "type": "page",
  "title": "TextMetrics",
  "links": {
    "mdn": "https://developer.mozilla.org/docs/Web/API/TextMetrics",
    "spec": "https://html.spec.whatwg.org/multipage/canvas.html#textmetrics",
    "github": "https://github.com/mdn/content/blob/main/files/en-us/web/api/textmetrics/index.md"
  },
  "content": {
    "intro": {
      "id": "ad63248f561cd29e1a6bc2f05be8d126",
      "tree": {
        "type": "root",
        "children": [
          {
            "type": "element",
            "tagName": "p",
            "properties": {},
            "children": [
              {
                "type": "text",
                "value": "The "
              },
              {
                "type": "element",
                "tagName": "strong",
                "properties": {},
                "children": [
                  {
                    "type": "element",
                    "tagName": "code",
                    "properties": {},
                    "children": [
                      {
                        "type": "text",
                        "value": "TextMetrics"
                      }
                    ]
                  }
                ]
              },
              {
                "type": "text",
                "value": " interface represents the dimensions of a piece of text in the canvas; a "
              },
              {
                "type": "element",
                "tagName": "code",
                "properties": {},
                "children": [
                  {
                    "type": "text",
                    "value": "TextMetrics"
                  }
                ]
              },
              {
                "type": "text",
                "value": " instance can be retrieved using the "
              },
              {
                "type": "element",
                "tagName": "a",
                "properties": {
                  "internal": "",
                  "href": "/api/CanvasRenderingContext2D/measureText"
                },
                "children": [
                  {
                    "type": "element",
                    "tagName": "code",
                    "properties": {},
                    "children": [
                      {
                        "type": "text",
                        "value": "CanvasRenderingContext2D.measureText()"
                      }
                    ]
                  }
                ]
              },
              {
                "type": "text",
                "value": " method."
              }
            ]
          }
        ],
        "data": {
          "quirksMode": false
        }
      }
    },
    "seeAlso": {
      "id": "ea42ca8a3ed811c29902e59846dc0e5b",
      "tree": {
        "type": "root",
        "children": [
          {
            "type": "element",
            "tagName": "ul",
            "properties": {},
            "children": [
              {
                "type": "text",
                "value": "\n"
              },
              {
                "type": "element",
                "tagName": "li",
                "properties": {},
                "children": [
                  {
                    "type": "text",
                    "value": "Creator method in "
                  },
                  {
                    "type": "element",
                    "tagName": "a",
                    "properties": {
                      "internal": "",
                      "href": "/api/CanvasRenderingContext2D"
                    },
                    "children": [
                      {
                        "type": "element",
                        "tagName": "code",
                        "properties": {},
                        "children": [
                          {
                            "type": "text",
                            "value": "CanvasRenderingContext2D"
                          }
                        ]
                      }
                    ]
                  }
                ]
              },
              {
                "type": "text",
                "value": "\n"
              },
              {
                "type": "element",
                "tagName": "li",
                "properties": {},
                "children": [
                  {
                    "type": "text",
                    "value": "The "
                  },
                  {
                    "type": "element",
                    "tagName": "a",
                    "properties": {
                      "internal": "",
                      "href": "/html/elements/canvas"
                    },
                    "children": [
                      {
                        "type": "element",
                        "tagName": "code",
                        "properties": {},
                        "children": [
                          {
                            "type": "text",
                            "value": "<canvas>"
                          }
                        ]
                      }
                    ]
                  },
                  {
                    "type": "text",
                    "value": " element and its associated interface, "
                  },
                  {
                    "type": "element",
                    "tagName": "a",
                    "properties": {
                      "internal": "",
                      "href": "/api/HTMLCanvasElement"
                    },
                    "children": [
                      {
                        "type": "element",
                        "tagName": "code",
                        "properties": {},
                        "children": [
                          {
                            "type": "text",
                            "value": "HTMLCanvasElement"
                          }
                        ]
                      }
                    ]
                  }
                ]
              },
              {
                "type": "text",
                "value": "\n"
              }
            ]
          }
        ],
        "data": {
          "quirksMode": false
        }
      }
    }
  },
  "commit": {
    "sha": "c27bad0d78568f4b8b4b15dfb476f86b597717b7",
    "date": "2022-06-02T19:19:04.000Z"
  },
  "usage": 0.96053,
  "support": {
    "chrome": {
      "name": "Chrome",
      "added": {
        "version": "1.0.0",
        "date": 1228953600
      },
      "removed": null,
      "usage": {
        "global": 0.24059999999999998,
        "relative": 1
      },
      "history": [
        {
          "notes": null,
          "added": {
            "version": "1.0.0",
            "date": 1228953600
          },
          "removed": null,
          "usage": {
            "global": 0.24059999999999998,
            "relative": 1
          }
        }
      ]
    },
    "chrome_android": {
      "name": "Chrome Android",
      "added": {
        "version": "18.0.0",
        "date": 1340755200
      },
      "removed": null,
      "usage": {
        "global": 0.3880200000000001,
        "relative": 1
      },
      "history": [
        {
          "notes": null,
          "added": {
            "version": "18.0.0",
            "date": 1340755200
          },
          "removed": null,
          "usage": {
            "global": 0.3880200000000001,
            "relative": 1
          }
        }
      ]
    },
    "edge": {
      "name": "Edge",
      "added": {
        "version": "12.0.0",
        "date": 1438041600
      },
      "removed": null,
      "usage": {
        "global": 0.041199999999999994,
        "relative": 1
      },
      "history": [
        {
          "notes": null,
          "added": {
            "version": "12.0.0",
            "date": 1438041600
          },
          "removed": null,
          "usage": {
            "global": 0.041199999999999994,
            "relative": 1
          }
        }
      ]
    },
    "firefox": {
      "name": "Firefox",
      "added": {
        "version": "1.5.0",
        "date": 1133222400
      },
      "removed": null,
      "usage": {
        "global": 0.029999999999999978,
        "relative": 1
      },
      "history": [
        {
          "notes": null,
          "added": {
            "version": "1.5.0",
            "date": 1133222400
          },
          "removed": null,
          "usage": {
            "global": 0.029999999999999978,
            "relative": 1
          }
        }
      ]
    },
    "firefox_android": {
      "name": "Firefox for Android",
      "added": {
        "version": "31.0.0",
        "date": 1405987200
      },
      "removed": null,
      "usage": {
        "global": null,
        "relative": null
      },
      "history": [
        {
          "notes": null,
          "added": {
            "version": "31.0.0",
            "date": 1405987200
          },
          "removed": null,
          "usage": {
            "global": null,
            "relative": null
          }
        }
      ]
    },
    "ie": {
      "name": "Internet Explorer",
      "added": {
        "version": "9.0.0",
        "date": 1300060800
      },
      "removed": null,
      "usage": {
        "global": 0.0062,
        "relative": 0.9841269841269841
      },
      "history": [
        {
          "notes": null,
          "added": {
            "version": "9.0.0",
            "date": 1300060800
          },
          "removed": null,
          "usage": {
            "global": 0.0062,
            "relative": 0.9841269841269841
          }
        }
      ]
    },
    "opera": {
      "name": "Opera",
      "added": {
        "version": "9.0.0",
        "date": 1150761600
      },
      "removed": null,
      "usage": {
        "global": 0.0176,
        "relative": 1
      },
      "history": [
        {
          "notes": null,
          "added": {
            "version": "9.0.0",
            "date": 1150761600
          },
          "removed": null,
          "usage": {
            "global": 0.0176,
            "relative": 1
          }
        }
      ]
    },
    "opera_android": {
      "name": "Opera Android",
      "added": {
        "version": "10.1.0",
        "date": 1289260800
      },
      "removed": null,
      "usage": {
        "global": null,
        "relative": null
      },
      "history": [
        {
          "notes": null,
          "added": {
            "version": "10.1.0",
            "date": 1289260800
          },
          "removed": null,
          "usage": {
            "global": null,
            "relative": null
          }
        }
      ]
    },
    "safari": {
      "name": "Safari",
      "added": {
        "version": "4.0.0",
        "date": 1244419200
      },
      "removed": null,
      "usage": {
        "global": 0.0348,
        "relative": 1
      },
      "history": [
        {
          "notes": null,
          "added": {
            "version": "4.0.0",
            "date": 1244419200
          },
          "removed": null,
          "usage": {
            "global": 0.0348,
            "relative": 1
          }
        }
      ]
    },
    "safari_ios": {
      "name": "Safari on iOS",
      "added": {
        "version": "3.2.0",
        "date": 1270252800
      },
      "removed": null,
      "usage": {
        "global": 0.17430999999999994,
        "relative": 1
      },
      "history": [
        {
          "notes": null,
          "added": {
            "version": "3.2.0",
            "date": 1270252800
          },
          "removed": null,
          "usage": {
            "global": 0.17430999999999994,
            "relative": 1
          }
        }
      ]
    },
    "samsunginternet_android": {
      "name": "Samsung Internet",
      "added": {
        "version": "1.0.0",
        "date": 1367020800
      },
      "removed": null,
      "usage": {
        "global": 0.02779999999999998,
        "relative": 1
      },
      "history": [
        {
          "notes": null,
          "added": {
            "version": "1.0.0",
            "date": 1367020800
          },
          "removed": null,
          "usage": {
            "global": 0.02779999999999998,
            "relative": 1
          }
        }
      ]
    },
    "webview_android": {
      "name": "WebView Android",
      "added": {
        "version": "37.0.0",
        "date": 1409702400
      },
      "removed": null,
      "usage": {
        "global": null,
        "relative": null
      },
      "history": [
        {
          "notes": null,
          "added": {
            "version": "37.0.0",
            "date": 1409702400
          },
          "removed": null,
          "usage": {
            "global": null,
            "relative": null
          }
        }
      ]
    }
  },
  "status": {
    "deprecated": false,
    "experimental": false,
    "standard_track": true
  }
}