{
  "self": [
    "api",
    "HTMLInputElement",
    "webkitEntries"
  ],
  "type": "page",
  "title": "HTMLInputElement.webkitEntries",
  "links": {
    "mdn": "https://developer.mozilla.org/docs/Web/API/HTMLInputElement/webkitEntries",
    "spec": "https://wicg.github.io/entries-api/#dom-htmlinputelement-webkitentries",
    "github": "https://github.com/mdn/content/blob/main/files/en-us/web/api/htmlinputelement/webkitentries/index.md"
  },
  "content": {
    "intro": {
      "id": "4273e8cf60751165a88037d885253686",
      "tree": {
        "type": "root",
        "children": [
          {
            "type": "element",
            "tagName": "p",
            "properties": {},
            "children": [
              {
                "type": "text",
                "value": "The read-only "
              },
              {
                "type": "element",
                "tagName": "strong",
                "properties": {},
                "children": [
                  {
                    "type": "element",
                    "tagName": "code",
                    "properties": {},
                    "children": [
                      {
                        "type": "text",
                        "value": "webkitEntries"
                      }
                    ]
                  }
                ]
              },
              {
                "type": "text",
                "value": "\nproperty of the "
              },
              {
                "type": "element",
                "tagName": "a",
                "properties": {
                  "internal": "",
                  "href": "/api/HTMLInputElement"
                },
                "children": [
                  {
                    "type": "element",
                    "tagName": "code",
                    "properties": {},
                    "children": [
                      {
                        "type": "text",
                        "value": "HTMLInputElement"
                      }
                    ]
                  }
                ]
              },
              {
                "type": "text",
                "value": " interface contains an array of file\nsystem entries (as objects based on "
              },
              {
                "type": "element",
                "tagName": "a",
                "properties": {
                  "internal": "",
                  "href": "/api/FileSystemEntry"
                },
                "children": [
                  {
                    "type": "element",
                    "tagName": "code",
                    "properties": {},
                    "children": [
                      {
                        "type": "text",
                        "value": "FileSystemEntry"
                      }
                    ]
                  }
                ]
              },
              {
                "type": "text",
                "value": ") representing files\nand/or directories selected by the user using an "
              },
              {
                "type": "element",
                "tagName": "a",
                "properties": {
                  "internal": "",
                  "href": "/html/elements/input"
                },
                "children": [
                  {
                    "type": "element",
                    "tagName": "code",
                    "properties": {},
                    "children": [
                      {
                        "type": "text",
                        "value": "<input>"
                      }
                    ]
                  }
                ]
              },
              {
                "type": "text",
                "value": " element of\ntype "
              },
              {
                "type": "element",
                "tagName": "code",
                "properties": {},
                "children": [
                  {
                    "type": "text",
                    "value": "file"
                  }
                ]
              },
              {
                "type": "text",
                "value": ", but only if that selection was made using drag-and-drop:\nselecting a file in the dialog will leave the property empty."
              }
            ]
          }
        ],
        "data": {
          "quirksMode": false
        }
      }
    },
    "seeAlso": {
      "id": "1eb7f9a773ef39148f87708e19dca723",
      "tree": {
        "type": "root",
        "children": [
          {
            "type": "element",
            "tagName": "ul",
            "properties": {},
            "children": [
              {
                "type": "text",
                "value": "\n"
              },
              {
                "type": "element",
                "tagName": "li",
                "properties": {},
                "children": [
                  {
                    "type": "element",
                    "tagName": "a",
                    "properties": {
                      "href": "/en-US/docs/Web/API/File_and_Directory_Entries_API"
                    },
                    "children": [
                      {
                        "type": "text",
                        "value": "File and Directory\nEntries API"
                      }
                    ]
                  }
                ]
              },
              {
                "type": "text",
                "value": "\n"
              },
              {
                "type": "element",
                "tagName": "li",
                "properties": {},
                "children": [
                  {
                    "type": "element",
                    "tagName": "a",
                    "properties": {
                      "href": "/en-US/docs/Web/API/File_and_Directory_Entries_API/Introduction"
                    },
                    "children": [
                      {
                        "type": "text",
                        "value": "Introduction\nto the File System API"
                      }
                    ]
                  }
                ]
              },
              {
                "type": "text",
                "value": "\n"
              },
              {
                "type": "element",
                "tagName": "li",
                "properties": {},
                "children": [
                  {
                    "type": "element",
                    "tagName": "a",
                    "properties": {
                      "internal": "",
                      "href": "/api/HTMLInputElement"
                    },
                    "children": [
                      {
                        "type": "element",
                        "tagName": "code",
                        "properties": {},
                        "children": [
                          {
                            "type": "text",
                            "value": "HTMLInputElement"
                          }
                        ]
                      }
                    ]
                  }
                ]
              },
              {
                "type": "text",
                "value": "\n"
              },
              {
                "type": "element",
                "tagName": "li",
                "properties": {},
                "children": [
                  {
                    "type": "element",
                    "tagName": "a",
                    "properties": {
                      "internal": "",
                      "href": "/api/FileSystemEntry"
                    },
                    "children": [
                      {
                        "type": "element",
                        "tagName": "code",
                        "properties": {},
                        "children": [
                          {
                            "type": "text",
                            "value": "FileSystemEntry"
                          }
                        ]
                      }
                    ]
                  }
                ]
              },
              {
                "type": "text",
                "value": "\n"
              },
              {
                "type": "element",
                "tagName": "li",
                "properties": {},
                "children": [
                  {
                    "type": "element",
                    "tagName": "a",
                    "properties": {
                      "internal": "",
                      "href": "/api/FileSystem"
                    },
                    "children": [
                      {
                        "type": "element",
                        "tagName": "code",
                        "properties": {},
                        "children": [
                          {
                            "type": "text",
                            "value": "FileSystem"
                          }
                        ]
                      }
                    ]
                  }
                ]
              },
              {
                "type": "text",
                "value": "\n"
              }
            ]
          }
        ],
        "data": {
          "quirksMode": false
        }
      }
    }
  },
  "commit": {
    "sha": "e54fd25240b825391b109769334b8e977c746aea",
    "date": "2022-03-30T06:51:38.000Z"
  },
  "usage": 0.9438500000000001,
  "support": {
    "chrome": {
      "name": "Chrome",
      "added": {
        "version": "22.0.0",
        "date": 1348531200
      },
      "removed": null,
      "usage": {
        "global": 0.24799999999999994,
        "relative": 1
      },
      "history": [
        {
          "notes": null,
          "added": {
            "version": "22.0.0",
            "date": 1348531200
          },
          "removed": null,
          "usage": {
            "global": 0.24799999999999994,
            "relative": 1
          }
        }
      ]
    },
    "chrome_android": {
      "name": "Chrome Android",
      "added": {
        "version": "25.0.0",
        "date": 1361923200
      },
      "removed": null,
      "usage": {
        "global": 0.37660000000000016,
        "relative": 1
      },
      "history": [
        {
          "notes": null,
          "added": {
            "version": "25.0.0",
            "date": 1361923200
          },
          "removed": null,
          "usage": {
            "global": 0.37660000000000016,
            "relative": 1
          }
        }
      ]
    },
    "edge": {
      "name": "Edge",
      "added": {
        "version": "79.0.0",
        "date": 1579046400
      },
      "removed": null,
      "usage": {
        "global": 0.039999999999999994,
        "relative": 0.970873786407767
      },
      "history": [
        {
          "notes": null,
          "added": {
            "version": "79.0.0",
            "date": 1579046400
          },
          "removed": null,
          "usage": {
            "global": 0.039999999999999994,
            "relative": 0.970873786407767
          }
        }
      ]
    },
    "firefox": {
      "name": "Firefox",
      "added": {
        "version": "50.0.0",
        "date": 1479168000
      },
      "removed": null,
      "usage": {
        "global": 0.031099999999999985,
        "relative": 0.9810725552050473
      },
      "history": [
        {
          "notes": null,
          "added": {
            "version": "50.0.0",
            "date": 1479168000
          },
          "removed": null,
          "usage": {
            "global": 0.031099999999999985,
            "relative": 0.9810725552050473
          }
        }
      ]
    },
    "firefox_android": {
      "name": "Firefox for Android",
      "added": null,
      "removed": null,
      "usage": {
        "global": null,
        "relative": null
      },
      "history": [
        {
          "notes": null,
          "added": null,
          "removed": null,
          "usage": {
            "global": null,
            "relative": null
          }
        }
      ]
    },
    "ie": {
      "name": "Internet Explorer",
      "added": null,
      "removed": null,
      "usage": {
        "global": null,
        "relative": null
      },
      "history": [
        {
          "notes": null,
          "added": null,
          "removed": null,
          "usage": {
            "global": null,
            "relative": null
          }
        }
      ]
    },
    "opera": {
      "name": "Opera",
      "added": {
        "version": "15.0.0",
        "date": 1372723200
      },
      "removed": null,
      "usage": {
        "global": 0.016200000000000003,
        "relative": 0.9938650306748467
      },
      "history": [
        {
          "notes": null,
          "added": {
            "version": "15.0.0",
            "date": 1372723200
          },
          "removed": null,
          "usage": {
            "global": 0.016200000000000003,
            "relative": 0.9938650306748467
          }
        }
      ]
    },
    "opera_android": {
      "name": "Opera Android",
      "added": {
        "version": "14.0.0",
        "date": 1369094400
      },
      "removed": null,
      "usage": {
        "global": null,
        "relative": null
      },
      "history": [
        {
          "notes": null,
          "added": {
            "version": "14.0.0",
            "date": 1369094400
          },
          "removed": null,
          "usage": {
            "global": null,
            "relative": null
          }
        }
      ]
    },
    "safari": {
      "name": "Safari",
      "added": {
        "version": "11.1.0",
        "date": 1523491200
      },
      "removed": null,
      "usage": {
        "global": 0.037,
        "relative": 0.9973045822102427
      },
      "history": [
        {
          "notes": null,
          "added": {
            "version": "11.1.0",
            "date": 1523491200
          },
          "removed": null,
          "usage": {
            "global": 0.037,
            "relative": 0.9973045822102427
          }
        }
      ]
    },
    "safari_ios": {
      "name": "Safari on iOS",
      "added": {
        "version": "11.3.0",
        "date": 1522281600
      },
      "removed": null,
      "usage": {
        "global": 0.16745000000000002,
        "relative": 0.97718253968254
      },
      "history": [
        {
          "notes": null,
          "added": {
            "version": "11.3.0",
            "date": 1522281600
          },
          "removed": null,
          "usage": {
            "global": 0.16745000000000002,
            "relative": 0.97718253968254
          }
        }
      ]
    },
    "samsunginternet_android": {
      "name": "Samsung Internet",
      "added": {
        "version": "1.5.0",
        "date": 1380067200
      },
      "removed": null,
      "usage": {
        "global": 0.027499999999999983,
        "relative": 0.996376811594203
      },
      "history": [
        {
          "notes": null,
          "added": {
            "version": "1.5.0",
            "date": 1380067200
          },
          "removed": null,
          "usage": {
            "global": 0.027499999999999983,
            "relative": 0.996376811594203
          }
        }
      ]
    },
    "webview_android": {
      "name": "WebView Android",
      "added": {
        "version": "37.0.0",
        "date": 1409702400
      },
      "removed": null,
      "usage": {
        "global": null,
        "relative": null
      },
      "history": [
        {
          "notes": null,
          "added": {
            "version": "37.0.0",
            "date": 1409702400
          },
          "removed": null,
          "usage": {
            "global": null,
            "relative": null
          }
        }
      ]
    }
  },
  "status": {
    "experimental": false,
    "standard_track": false,
    "deprecated": false
  }
}