{
  "self": [
    "webextensions",
    "manifest",
    "chrome_url_overrides"
  ],
  "type": "page",
  "commit": {
    "sha": "934fa5fcedcbd1855c45782424b9ff6e6a04e89a",
    "date": "2022-02-18T09:16:12.000Z"
  },
  "title": "chrome_url_overrides",
  "links": {
    "mdn": "https://developer.mozilla.org/docs/Mozilla/Add-ons/WebExtensions/manifest.json/chrome_url_overrides",
    "github": "https://github.com/mdn/content/blob/main/files/en-us/mozilla/add-ons/webextensions/manifest.json/chrome_url_overrides/index.md"
  },
  "content": {
    "intro": {
      "id": "923fc4df0ece97ddc1045fc0e44edc38",
      "tree": {
        "type": "root",
        "children": [
          {
            "type": "element",
            "tagName": "p",
            "properties": {},
            "children": [
              {
                "type": "text",
                "value": "Use the "
              },
              {
                "type": "element",
                "tagName": "code",
                "properties": {},
                "children": [
                  {
                    "type": "text",
                    "value": "chrome_url_overrides"
                  }
                ]
              },
              {
                "type": "text",
                "value": " key to provide a custom replacement for the documents loaded into various special pages usually provided by the browser itself."
              }
            ]
          }
        ],
        "data": {
          "quirksMode": false
        }
      }
    }
  },
  "usage": 0.36213319,
  "support": {
    "chrome": {
      "name": "Chrome",
      "added": {
        "version": "1.0.0",
        "date": 1228953600
      },
      "removed": null,
      "usage": {
        "global": 0.26085710999999995,
        "relative": 1
      },
      "history": [
        {
          "notes": null,
          "added": {
            "version": "1.0.0",
            "date": 1228953600
          },
          "removed": null,
          "usage": {
            "global": 0.26085710999999995,
            "relative": 1
          }
        }
      ]
    },
    "edge": {
      "name": "Edge",
      "added": {
        "version": "79.0.0",
        "date": 1579046400
      },
      "removed": null,
      "usage": {
        "global": 0.040041789999999994,
        "relative": 0.9706957060756193
      },
      "history": [
        {
          "notes": null,
          "added": {
            "version": "79.0.0",
            "date": 1579046400
          },
          "removed": null,
          "usage": {
            "global": 0.040041789999999994,
            "relative": 0.9706957060756193
          }
        }
      ]
    },
    "firefox": {
      "name": "Firefox",
      "added": {
        "version": "54.0.0",
        "date": 1497312000
      },
      "removed": null,
      "usage": {
        "global": 0.037308539999999994,
        "relative": 0.8950246819131487
      },
      "history": [
        {
          "notes": null,
          "added": {
            "version": "54.0.0",
            "date": 1497312000
          },
          "removed": null,
          "usage": {
            "global": 0.037308539999999994,
            "relative": 0.8950246819131487
          }
        }
      ]
    },
    "firefox_android": {
      "name": "Firefox for Android",
      "added": null,
      "removed": null,
      "usage": {
        "global": null,
        "relative": null
      },
      "history": [
        {
          "notes": null,
          "added": null,
          "removed": null,
          "usage": {
            "global": null,
            "relative": null
          }
        }
      ]
    },
    "opera": {
      "name": "Opera",
      "added": null,
      "removed": null,
      "usage": {
        "global": null,
        "relative": null
      },
      "history": [
        {
          "notes": null,
          "added": null,
          "removed": null,
          "usage": {
            "global": null,
            "relative": null
          }
        }
      ]
    },
    "safari": {
      "name": "Safari",
      "added": {
        "version": "14.1.0",
        "date": 1619395200
      },
      "removed": null,
      "usage": {
        "global": 0.02392575,
        "relative": 0.715414707747676
      },
      "history": [
        {
          "notes": null,
          "added": {
            "version": "14.1.0",
            "date": 1619395200
          },
          "removed": null,
          "usage": {
            "global": 0.02392575,
            "relative": 0.715414707747676
          }
        }
      ]
    }
  }
}